wideq/__init__.py
wideq/ac.py
wideq/client.py
wideq/core.py
wideq/dehum.py
wideq/dishwasher.py
wideq/dryer.py
wideq/setup.py
wideq/util.py
wideq/washer.py
wideq_gu-0.0.1b0.dist-info/LICENSE
wideq_gu-0.0.1b0.dist-info/METADATA
wideq_gu-0.0.1b0.dist-info/WHEEL
wideq_gu-0.0.1b0.dist-info/top_level.txt
wideq_gu-0.0.1b0.dist-info/RECORD
