Metadata-Version: 2.1
Name: wideq-gu
Version: 0.0.1b0
Summary: LG SmartThinQ API client for Korean
Home-page: https://github.com/gugu927/wideq
Author: gugu927
Author-email: kimcg0927@gmail.com
License: MIT
Platform: ALL
Classifier: Intended Audience :: Developers
Classifier: License :: OSI Approved :: MIT License
Classifier: Programming Language :: Python :: 3
Requires-Dist: requests
